trinsic/__init__.py
trinsic/service_clients/__init__.py
trinsic/service_clients/service_client_credentials.py
trinsic/service_clients/credentials/__init__.py
trinsic/service_clients/credentials/credentials_client.py
trinsic/service_clients/credentials/version.py
trinsic/service_clients/credentials/models/__init__.py
trinsic/service_clients/credentials/models/agent_endpoint.py
trinsic/service_clients/credentials/models/agent_endpoint_py3.py
trinsic/service_clients/credentials/models/attribute_filter.py
trinsic/service_clients/credentials/models/attribute_filter_py3.py
trinsic/service_clients/credentials/models/attribute_value.py
trinsic/service_clients/credentials/models/attribute_value_py3.py
trinsic/service_clients/credentials/models/basic_message_contract.py
trinsic/service_clients/credentials/models/basic_message_contract_py3.py
trinsic/service_clients/credentials/models/basic_message_parameters.py
trinsic/service_clients/credentials/models/basic_message_parameters_py3.py
trinsic/service_clients/credentials/models/basic_message_record.py
trinsic/service_clients/credentials/models/basic_message_record_py3.py
trinsic/service_clients/credentials/models/connection_contract.py
trinsic/service_clients/credentials/models/connection_contract_py3.py
trinsic/service_clients/credentials/models/connection_invitation_parameters.py
trinsic/service_clients/credentials/models/connection_invitation_parameters_py3.py
trinsic/service_clients/credentials/models/credential_contract.py
trinsic/service_clients/credentials/models/credential_contract_py3.py
trinsic/service_clients/credentials/models/credential_definition_contract.py
trinsic/service_clients/credentials/models/credential_definition_contract_py3.py
trinsic/service_clients/credentials/models/credential_definition_from_schema_parameters.py
trinsic/service_clients/credentials/models/credential_definition_from_schema_parameters_py3.py
trinsic/service_clients/credentials/models/credential_definition_parameters.py
trinsic-1.1.5018.dist-info/LICENSE.txt
trinsic-1.1.5018.dist-info/METADATA
trinsic-1.1.5018.dist-info/WHEEL
trinsic-1.1.5018.dist-info/top_level.txt
trinsic-1.1.5018.dist-info/RECORD
