Metadata-Version: 1.0
Name: trinsic
Version: 1.1.5018
Summary: Service Clients to access Trinsic APIs
Home-page: https://github.com/streetcred-id/service-clients/tree/master/python/package
Author: UNKNOWN
Author-email: support@trinsic.id
License: UNKNOWN
Keywords: Trinsic
Platform: UNKNOWN
